TurboTalk_VAI/__init__.py
TurboTalk_VAI/turbo_talk.py
TurboTalk_VAI-0.4.dist-info/METADATA
TurboTalk_VAI-0.4.dist-info/WHEEL
TurboTalk_VAI-0.4.dist-info/top_level.txt
TurboTalk_VAI-0.4.dist-info/RECORD
