Metadata-Version: 2.1
Name: TurboTalk_VAI
Version: 0.4
Requires-Dist: SpeechRecognition
Requires-Dist: pyttsx3
Requires-Dist: colorama
Requires-Dist: TurboTalk-Custom
